griffe_runtime_objects-0.3.0.dist-info/METADATA
griffe_runtime_objects-0.3.0.dist-info/WHEEL
griffe_runtime_objects-0.3.0.dist-info/entry_points.txt
griffe_runtime_objects-0.3.0.dist-info/licenses/LICENSE
griffe_runtime_objects/__init__.py
griffe_runtime_objects/_internal/__init__.py
griffe_runtime_objects/_internal/debug.py
griffe_runtime_objects/_internal/extension.py
griffe_runtime_objects/py.typed
griffe_runtime_objects-0.3.0.dist-info/RECORD
